{"time":{"updated":"Sep 10, 2024 02:25:39 UTC","updatedISO":"2024-09-10T02:25:39+00:00","updateduk":"Sep 10, 2024 at 03:25 BST"},"disclaimer":"This data was produced from the CoinDesk Bitcoin Price Index (USD). Non-USD currency data converted using hourly conversion rate from openexchangerates.org","chartName":"Bitcoin","bpi":{"USD":{"code":"USD","symbol":"&#36;","rate":"56,693.599","description":"United States Dollar","rate_float":56693.5992},"GBP":{"code":"GBP","symbol":"&pound;","rate":"43,401.105","description":"British Pound Sterling","rate_float":43401.1046},"EUR":{"code":"EUR","symbol":"&euro;","rate":"51,395.526","description":"Euro","rate_float":51395.5257},"CNY":{"code":"CNY","symbol":"&yen;","rate":"403,437.322","description":"Chinese Yuan","rate_float":403437.3215}}}