{"time":{"updated":"Jan 10, 2023 21:05:00 UTC","updatedISO":"2023-01-10T21:05:00+00:00","updateduk":"Jan 10, 2023 at 21:05 GMT"},"disclaimer":"This data was produced from the CoinDesk Bitcoin Price Index (USD). Non-USD currency data converted using hourly conversion rate from openexchangerates.org","chartName":"Bitcoin","bpi":{"USD":{"code":"USD","symbol":"&#36;","rate":"17,459.6727","description":"United States Dollar","rate_float":17459.6727},"GBP":{"code":"GBP","symbol":"&pound;","rate":"14,589.1628","description":"British Pound Sterling","rate_float":14589.1628},"EUR":{"code":"EUR","symbol":"&euro;","rate":"17,008.2703","description":"Euro","rate_float":17008.2703},"CNY":{"code":"CNY","symbol":"&yen;","rate":"40,202.5000","description":"Chinese Yuan","rate_float":40202.5}}}