{"time":{"updated":"Nov 13, 2024 15:06:38 UTC","updatedISO":"2024-11-13T15:06:38+00:00","updateduk":"Nov 13, 2024 at 15:06 GMT"},"disclaimer":"This data was produced from the CoinDesk Bitcoin Price Index (USD). Non-USD currency data converted using hourly conversion rate from openexchangerates.org","chartName":"Bitcoin","bpi":{"USD":{"code":"USD","symbol":"&#36;","rate":"90,997.069","description":"United States Dollar","rate_float":90997.0687},"GBP":{"code":"GBP","symbol":"&pound;","rate":"71,345.615","description":"British Pound Sterling","rate_float":71345.6147},"EUR":{"code":"EUR","symbol":"&euro;","rate":"85,550.166","description":"Euro","rate_float":85550.1662},"CNY":{"code":"CNY","symbol":"&yen;","rate":"656,161.663","description":"Chinese Yuan","rate_float":656161.663}}}