{"time":{"updated":"Mar 20, 2024 18:06:14 UTC","updatedISO":"2024-03-20T18:06:14+00:00","updateduk":"Mar 20, 2024 at 18:06 GMT"},"disclaimer":"This data was produced from the CoinDesk Bitcoin Price Index (USD). Non-USD currency data converted using hourly conversion rate from openexchangerates.org","chartName":"Bitcoin","bpi":{"USD":{"code":"USD","symbol":"&#36;","rate":"64,597.476","description":"United States Dollar","rate_float":64597.476},"GBP":{"code":"GBP","symbol":"&pound;","rate":"50,791.574","description":"British Pound Sterling","rate_float":50791.5742},"EUR":{"code":"EUR","symbol":"&euro;","rate":"59,478.578","description":"Euro","rate_float":59478.5782},"CNY":{"code":"CNY","symbol":"&yen;","rate":"465,056.609","description":"Chinese Yuan","rate_float":465056.6088}}}