{"time":{"updated":"Jan 23, 2024 00:23:46 UTC","updatedISO":"2024-01-23T00:23:46+00:00","updateduk":"Jan 23, 2024 at 00:23 GMT"},"disclaimer":"This data was produced from the CoinDesk Bitcoin Price Index (USD). Non-USD currency data converted using hourly conversion rate from openexchangerates.org","chartName":"Bitcoin","bpi":{"USD":{"code":"USD","symbol":"&#36;","rate":"39,806.552","description":"United States Dollar","rate_float":39806.5515},"GBP":{"code":"GBP","symbol":"&pound;","rate":"31,319.158","description":"British Pound Sterling","rate_float":31319.1578},"EUR":{"code":"EUR","symbol":"&euro;","rate":"36,581.146","description":"Euro","rate_float":36581.146},"CNY":{"code":"CNY","symbol":"&yen;","rate":"286,364.351","description":"Chinese Yuan","rate_float":286364.3505}}}