{"time":{"updated":"May 26, 2024 03:06:21 UTC","updatedISO":"2024-05-26T03:06:21+00:00","updateduk":"May 26, 2024 at 04:06 BST"},"disclaimer":"This data was produced from the CoinDesk Bitcoin Price Index (USD). Non-USD currency data converted using hourly conversion rate from openexchangerates.org","chartName":"Bitcoin","bpi":{"USD":{"code":"USD","symbol":"&#36;","rate":"68,926.163","description":"United States Dollar","rate_float":68926.1631},"GBP":{"code":"GBP","symbol":"&pound;","rate":"54,093.666","description":"British Pound Sterling","rate_float":54093.6664},"EUR":{"code":"EUR","symbol":"&euro;","rate":"63,535.172","description":"Euro","rate_float":63535.1722},"CNY":{"code":"CNY","symbol":"&yen;","rate":"490,099.483","description":"Chinese Yuan","rate_float":490099.4828}}}