{"time":{"updated":"Jun 22, 2024 05:06:10 UTC","updatedISO":"2024-06-22T05:06:10+00:00","updateduk":"Jun 22, 2024 at 06:06 BST"},"disclaimer":"This data was produced from the CoinDesk Bitcoin Price Index (USD). Non-USD currency data converted using hourly conversion rate from openexchangerates.org","chartName":"Bitcoin","bpi":{"USD":{"code":"USD","symbol":"&#36;","rate":"64,353.785","description":"United States Dollar","rate_float":64353.7849},"GBP":{"code":"GBP","symbol":"&pound;","rate":"50,858.475","description":"British Pound Sterling","rate_float":50858.4745},"EUR":{"code":"EUR","symbol":"&euro;","rate":"60,152.126","description":"Euro","rate_float":60152.1263},"CNY":{"code":"CNY","symbol":"&yen;","rate":"467,292.138","description":"Chinese Yuan","rate_float":467292.1384}}}