{"time":{"updated":"Nov 6, 2024 18:08:28 UTC","updatedISO":"2024-11-06T18:08:28+00:00","updateduk":"Nov 6, 2024 at 18:08 GMT"},"disclaimer":"This data was produced from the CoinDesk Bitcoin Price Index (USD). Non-USD currency data converted using hourly conversion rate from openexchangerates.org","chartName":"Bitcoin","bpi":{"USD":{"code":"USD","symbol":"&#36;","rate":"74,693.84","description":"United States Dollar","rate_float":74693.8399},"GBP":{"code":"GBP","symbol":"&pound;","rate":"57,921.861","description":"British Pound Sterling","rate_float":57921.861},"EUR":{"code":"EUR","symbol":"&euro;","rate":"69,601.811","description":"Euro","rate_float":69601.8114},"CNY":{"code":"CNY","symbol":"&yen;","rate":"536,122.505","description":"Chinese Yuan","rate_float":536122.5052}}}