{"time":{"updated":"Apr 20, 2024 12:08:04 UTC","updatedISO":"2024-04-20T12:08:04+00:00","updateduk":"Apr 20, 2024 at 13:08 BST"},"disclaimer":"This data was produced from the CoinDesk Bitcoin Price Index (USD). Non-USD currency data converted using hourly conversion rate from openexchangerates.org","chartName":"Bitcoin","bpi":{"USD":{"code":"USD","symbol":"&#36;","rate":"63,880.497","description":"United States Dollar","rate_float":63880.4967},"GBP":{"code":"GBP","symbol":"&pound;","rate":"51,645.657","description":"British Pound Sterling","rate_float":51645.6568},"EUR":{"code":"EUR","symbol":"&euro;","rate":"59,911.346","description":"Euro","rate_float":59911.3459},"CNY":{"code":"CNY","symbol":"&yen;","rate":"462,450.08","description":"Chinese Yuan","rate_float":462450.0795}}}