{"time":{"updated":"Jan 16, 2024 08:07:06 UTC","updatedISO":"2024-01-16T08:07:06+00:00","updateduk":"Jan 16, 2024 at 08:07 GMT"},"disclaimer":"This data was produced from the CoinDesk Bitcoin Price Index (USD). Non-USD currency data converted using hourly conversion rate from openexchangerates.org","chartName":"Bitcoin","bpi":{"USD":{"code":"USD","symbol":"&#36;","rate":"42,750.522","description":"United States Dollar","rate_float":42750.5221},"GBP":{"code":"GBP","symbol":"&pound;","rate":"33,703.742","description":"British Pound Sterling","rate_float":33703.7421},"EUR":{"code":"EUR","symbol":"&euro;","rate":"39,156.999","description":"Euro","rate_float":39156.9988},"CNY":{"code":"CNY","symbol":"&yen;","rate":"304,281.116","description":"Chinese Yuan","rate_float":304281.1164}}}