{"time":{"updated":"Dec 3, 2024 19:06:11 UTC","updatedISO":"2024-12-03T19:06:11+00:00","updateduk":"Dec 3, 2024 at 19:06 GMT"},"disclaimer":"This data was produced from the CoinDesk Bitcoin Price Index (USD). Non-USD currency data converted using hourly conversion rate from openexchangerates.org","chartName":"Bitcoin","bpi":{"USD":{"code":"USD","symbol":"&#36;","rate":"95,497.771","description":"United States Dollar","rate_float":95497.7707},"GBP":{"code":"GBP","symbol":"&pound;","rate":"75,245.177","description":"British Pound Sterling","rate_float":75245.1765},"EUR":{"code":"EUR","symbol":"&euro;","rate":"90,707.03","description":"Euro","rate_float":90707.0295},"CNY":{"code":"CNY","symbol":"&yen;","rate":"695,777.658","description":"Chinese Yuan","rate_float":695777.6577}}}