{"time":{"updated":"Apr 13, 2023 01:32:00 UTC","updatedISO":"2023-04-13T01:32:00+00:00","updateduk":"Apr 13, 2023 at 02:32 BST"},"disclaimer":"This data was produced from the CoinDesk Bitcoin Price Index (USD). Non-USD currency data converted using hourly conversion rate from openexchangerates.org","chartName":"Bitcoin","bpi":{"USD":{"code":"USD","symbol":"&#36;","rate":"29,996.7874","description":"United States Dollar","rate_float":29996.7874},"GBP":{"code":"GBP","symbol":"&pound;","rate":"25,065.0756","description":"British Pound Sterling","rate_float":25065.0756},"EUR":{"code":"EUR","symbol":"&euro;","rate":"29,221.2504","description":"Euro","rate_float":29221.2504},"CNY":{"code":"CNY","symbol":"&yen;","rate":"40,202.5000","description":"Chinese Yuan","rate_float":40202.5}}}