{"time":{"updated":"Aug 17, 2024 00:24:45 UTC","updatedISO":"2024-08-17T00:24:45+00:00","updateduk":"Aug 17, 2024 at 01:24 BST"},"disclaimer":"This data was produced from the CoinDesk Bitcoin Price Index (USD). Non-USD currency data converted using hourly conversion rate from openexchangerates.org","chartName":"Bitcoin","bpi":{"USD":{"code":"USD","symbol":"&#36;","rate":"59,000.451","description":"United States Dollar","rate_float":59000.4508},"GBP":{"code":"GBP","symbol":"&pound;","rate":"45,553.186","description":"British Pound Sterling","rate_float":45553.1861},"EUR":{"code":"EUR","symbol":"&euro;","rate":"53,483.614","description":"Euro","rate_float":53483.6137},"CNY":{"code":"CNY","symbol":"&yen;","rate":"422,738.23","description":"Chinese Yuan","rate_float":422738.2302}}}