{"time":{"updated":"Dec 29, 2024 20:06:40 UTC","updatedISO":"2024-12-29T20:06:40+00:00","updateduk":"Dec 29, 2024 at 20:06 GMT"},"disclaimer":"This data was produced from the CoinDesk Bitcoin Price Index (USD). Non-USD currency data converted using hourly conversion rate from openexchangerates.org","chartName":"Bitcoin","bpi":{"USD":{"code":"USD","symbol":"&#36;","rate":"93,266.564","description":"United States Dollar","rate_float":93266.5643},"GBP":{"code":"GBP","symbol":"&pound;","rate":"74,378.22","description":"British Pound Sterling","rate_float":74378.2197},"EUR":{"code":"EUR","symbol":"&euro;","rate":"89,477.237","description":"Euro","rate_float":89477.2371},"CNY":{"code":"CNY","symbol":"&yen;","rate":"680,715.346","description":"Chinese Yuan","rate_float":680715.3462}}}