{"time":{"updated":"Apr 4, 2024 14:07:04 UTC","updatedISO":"2024-04-04T14:07:04+00:00","updateduk":"Apr 4, 2024 at 15:07 BST"},"disclaimer":"This data was produced from the CoinDesk Bitcoin Price Index (USD). Non-USD currency data converted using hourly conversion rate from openexchangerates.org","chartName":"Bitcoin","bpi":{"USD":{"code":"USD","symbol":"&#36;","rate":"67,482.57","description":"United States Dollar","rate_float":67482.5702},"GBP":{"code":"GBP","symbol":"&pound;","rate":"53,266.759","description":"British Pound Sterling","rate_float":53266.7594},"EUR":{"code":"EUR","symbol":"&euro;","rate":"62,083.222","description":"Euro","rate_float":62083.2222},"CNY":{"code":"CNY","symbol":"&yen;","rate":"488,229.647","description":"Chinese Yuan","rate_float":488229.6469}}}