{"time":{"updated":"Sep 19, 2023 19:04:00 UTC","updatedISO":"2023-09-19T19:04:00+00:00","updateduk":"Sep 19, 2023 at 20:04 BST"},"disclaimer":"This data was produced from the CoinDesk Bitcoin Price Index (USD). Non-USD currency data converted using hourly conversion rate from openexchangerates.org","chartName":"Bitcoin","bpi":{"USD":{"code":"USD","symbol":"&#36;","rate":"27,145.4664","description":"United States Dollar","rate_float":27145.4664},"GBP":{"code":"GBP","symbol":"&pound;","rate":"22,682.5346","description":"British Pound Sterling","rate_float":22682.5346},"EUR":{"code":"EUR","symbol":"&euro;","rate":"26,443.6475","description":"Euro","rate_float":26443.6475},"CNY":{"code":"CNY","symbol":"&yen;","rate":"40,202.5000","description":"Chinese Yuan","rate_float":40202.5}}}