{"time":{"updated":"Nov 30, 2024 12:43:20 UTC","updatedISO":"2024-11-30T12:43:20+00:00","updateduk":"Nov 30, 2024 at 12:43 GMT"},"disclaimer":"This data was produced from the CoinDesk Bitcoin Price Index (USD). Non-USD currency data converted using hourly conversion rate from openexchangerates.org","chartName":"Bitcoin","bpi":{"USD":{"code":"USD","symbol":"&#36;","rate":"96,480.716","description":"United States Dollar","rate_float":96480.716},"GBP":{"code":"GBP","symbol":"&pound;","rate":"75,772.192","description":"British Pound Sterling","rate_float":75772.1916},"EUR":{"code":"EUR","symbol":"&euro;","rate":"91,208.817","description":"Euro","rate_float":91208.8167},"CNY":{"code":"CNY","symbol":"&yen;","rate":"698,684.401","description":"Chinese Yuan","rate_float":698684.4012}}}