{"time":{"updated":"Jun 15, 2024 04:06:52 UTC","updatedISO":"2024-06-15T04:06:52+00:00","updateduk":"Jun 15, 2024 at 05:06 BST"},"disclaimer":"This data was produced from the CoinDesk Bitcoin Price Index (USD). Non-USD currency data converted using hourly conversion rate from openexchangerates.org","chartName":"Bitcoin","bpi":{"USD":{"code":"USD","symbol":"&#36;","rate":"66,369.037","description":"United States Dollar","rate_float":66369.0373},"GBP":{"code":"GBP","symbol":"&pound;","rate":"52,370.414","description":"British Pound Sterling","rate_float":52370.4136},"EUR":{"code":"EUR","symbol":"&euro;","rate":"61,902.733","description":"Euro","rate_float":61902.733},"CNY":{"code":"CNY","symbol":"&yen;","rate":"481,520.64","description":"Chinese Yuan","rate_float":481520.6396}}}