{"time":{"updated":"Apr 20, 2024 22:06:05 UTC","updatedISO":"2024-04-20T22:06:05+00:00","updateduk":"Apr 20, 2024 at 23:06 BST"},"disclaimer":"This data was produced from the CoinDesk Bitcoin Price Index (USD). Non-USD currency data converted using hourly conversion rate from openexchangerates.org","chartName":"Bitcoin","bpi":{"USD":{"code":"USD","symbol":"&#36;","rate":"64,833.913","description":"United States Dollar","rate_float":64833.913},"GBP":{"code":"GBP","symbol":"&pound;","rate":"52,416.468","description":"British Pound Sterling","rate_float":52416.4682},"EUR":{"code":"EUR","symbol":"&euro;","rate":"60,805.523","description":"Euro","rate_float":60805.5227},"CNY":{"code":"CNY","symbol":"&yen;","rate":"469,352.147","description":"Chinese Yuan","rate_float":469352.1465}}}