{"time":{"updated":"Mar 28, 2024 09:06:15 UTC","updatedISO":"2024-03-28T09:06:15+00:00","updateduk":"Mar 28, 2024 at 09:06 GMT"},"disclaimer":"This data was produced from the CoinDesk Bitcoin Price Index (USD). Non-USD currency data converted using hourly conversion rate from openexchangerates.org","chartName":"Bitcoin","bpi":{"USD":{"code":"USD","symbol":"&#36;","rate":"70,843.49","description":"United States Dollar","rate_float":70843.4902},"GBP":{"code":"GBP","symbol":"&pound;","rate":"56,149.629","description":"British Pound Sterling","rate_float":56149.6293},"EUR":{"code":"EUR","symbol":"&euro;","rate":"65,586.62","description":"Euro","rate_float":65586.6198},"CNY":{"code":"CNY","symbol":"&yen;","rate":"511,915.06","description":"Chinese Yuan","rate_float":511915.0599}}}