{"time":{"updated":"May 17, 2024 14:06:16 UTC","updatedISO":"2024-05-17T14:06:16+00:00","updateduk":"May 17, 2024 at 15:06 BST"},"disclaimer":"This data was produced from the CoinDesk Bitcoin Price Index (USD). Non-USD currency data converted using hourly conversion rate from openexchangerates.org","chartName":"Bitcoin","bpi":{"USD":{"code":"USD","symbol":"&#36;","rate":"66,079.945","description":"United States Dollar","rate_float":66079.9447},"GBP":{"code":"GBP","symbol":"&pound;","rate":"52,196.68","description":"British Pound Sterling","rate_float":52196.6804},"EUR":{"code":"EUR","symbol":"&euro;","rate":"60,942.361","description":"Euro","rate_float":60942.3611},"CNY":{"code":"CNY","symbol":"&yen;","rate":"477,500.288","description":"Chinese Yuan","rate_float":477500.2881}}}