{"time":{"updated":"Sep 24, 2024 18:08:04 UTC","updatedISO":"2024-09-24T18:08:04+00:00","updateduk":"Sep 24, 2024 at 19:08 BST"},"disclaimer":"This data was produced from the CoinDesk Bitcoin Price Index (USD). Non-USD currency data converted using hourly conversion rate from openexchangerates.org","chartName":"Bitcoin","bpi":{"USD":{"code":"USD","symbol":"&#36;","rate":"63,790.374","description":"United States Dollar","rate_float":63790.3738},"GBP":{"code":"GBP","symbol":"&pound;","rate":"47,616.771","description":"British Pound Sterling","rate_float":47616.7711},"EUR":{"code":"EUR","symbol":"&euro;","rate":"57,147.244","description":"Euro","rate_float":57147.2443},"CNY":{"code":"CNY","symbol":"&yen;","rate":"448,567.53","description":"Chinese Yuan","rate_float":448567.5298}}}