{"time":{"updated":"Jul 17, 2024 08:07:47 UTC","updatedISO":"2024-07-17T08:07:47+00:00","updateduk":"Jul 17, 2024 at 09:07 BST"},"disclaimer":"This data was produced from the CoinDesk Bitcoin Price Index (USD). Non-USD currency data converted using hourly conversion rate from openexchangerates.org","chartName":"Bitcoin","bpi":{"USD":{"code":"USD","symbol":"&#36;","rate":"65,154.293","description":"United States Dollar","rate_float":65154.2934},"GBP":{"code":"GBP","symbol":"&pound;","rate":"50,167.242","description":"British Pound Sterling","rate_float":50167.2422},"EUR":{"code":"EUR","symbol":"&euro;","rate":"59,787.665","description":"Euro","rate_float":59787.6646},"CNY":{"code":"CNY","symbol":"&yen;","rate":"473,573.982","description":"Chinese Yuan","rate_float":473573.9818}}}