{"time":{"updated":"Dec 17, 2024 11:06:18 UTC","updatedISO":"2024-12-17T11:06:18+00:00","updateduk":"Dec 17, 2024 at 11:06 GMT"},"disclaimer":"This data was produced from the CoinDesk Bitcoin Price Index (USD). Non-USD currency data converted using hourly conversion rate from openexchangerates.org","chartName":"Bitcoin","bpi":{"USD":{"code":"USD","symbol":"&#36;","rate":"107,531.999","description":"United States Dollar","rate_float":107531.9987},"GBP":{"code":"GBP","symbol":"&pound;","rate":"84,140.886","description":"British Pound Sterling","rate_float":84140.8856},"EUR":{"code":"EUR","symbol":"&euro;","rate":"102,107.009","description":"Euro","rate_float":102107.0093},"CNY":{"code":"CNY","symbol":"&yen;","rate":"779,574.731","description":"Chinese Yuan","rate_float":779574.7308}}}