{"time":{"updated":"Feb 9, 2024 10:05:56 UTC","updatedISO":"2024-02-09T10:05:56+00:00","updateduk":"Feb 9, 2024 at 10:05 GMT"},"disclaimer":"This data was produced from the CoinDesk Bitcoin Price Index (USD). Non-USD currency data converted using hourly conversion rate from openexchangerates.org","chartName":"Bitcoin","bpi":{"USD":{"code":"USD","symbol":"&#36;","rate":"46,605.648","description":"United States Dollar","rate_float":46605.6476},"GBP":{"code":"GBP","symbol":"&pound;","rate":"36,939.03","description":"British Pound Sterling","rate_float":36939.0304},"EUR":{"code":"EUR","symbol":"&euro;","rate":"43,260.061","description":"Euro","rate_float":43260.0612},"CNY":{"code":"CNY","symbol":"&yen;","rate":"331,925.423","description":"Chinese Yuan","rate_float":331925.4225}}}