{"time":{"updated":"Jan 10, 2024 00:23:18 UTC","updatedISO":"2024-01-10T00:23:18+00:00","updateduk":"Jan 10, 2024 at 00:23 GMT"},"disclaimer":"This data was produced from the CoinDesk Bitcoin Price Index (USD). Non-USD currency data converted using hourly conversion rate from openexchangerates.org","chartName":"Bitcoin","bpi":{"USD":{"code":"USD","symbol":"&#36;","rate":"46,103.501","description":"United States Dollar","rate_float":46103.5012},"GBP":{"code":"GBP","symbol":"&pound;","rate":"36,268.61","description":"British Pound Sterling","rate_float":36268.6101},"EUR":{"code":"EUR","symbol":"&euro;","rate":"42,173.362","description":"Euro","rate_float":42173.3622},"CNY":{"code":"CNY","symbol":"&yen;","rate":"327,869.659","description":"Chinese Yuan","rate_float":327869.6594}}}