{"time":{"updated":"Jun 8, 2024 22:05:57 UTC","updatedISO":"2024-06-08T22:05:57+00:00","updateduk":"Jun 8, 2024 at 23:05 BST"},"disclaimer":"This data was produced from the CoinDesk Bitcoin Price Index (USD). Non-USD currency data converted using hourly conversion rate from openexchangerates.org","chartName":"Bitcoin","bpi":{"USD":{"code":"USD","symbol":"&#36;","rate":"69,534.708","description":"United States Dollar","rate_float":69534.7075},"GBP":{"code":"GBP","symbol":"&pound;","rate":"54,631.264","description":"British Pound Sterling","rate_float":54631.2641},"EUR":{"code":"EUR","symbol":"&euro;","rate":"64,340.465","description":"Euro","rate_float":64340.4649},"CNY":{"code":"CNY","symbol":"&yen;","rate":"503,848.491","description":"Chinese Yuan","rate_float":503848.4908}}}