{"time":{"updated":"Sep 7, 2024 12:08:58 UTC","updatedISO":"2024-09-07T12:08:58+00:00","updateduk":"Sep 7, 2024 at 13:08 BST"},"disclaimer":"This data was produced from the CoinDesk Bitcoin Price Index (USD). Non-USD currency data converted using hourly conversion rate from openexchangerates.org","chartName":"Bitcoin","bpi":{"USD":{"code":"USD","symbol":"&#36;","rate":"54,468.298","description":"United States Dollar","rate_float":54468.2977},"GBP":{"code":"GBP","symbol":"&pound;","rate":"41,477.554","description":"British Pound Sterling","rate_float":41477.5542},"EUR":{"code":"EUR","symbol":"&euro;","rate":"49,114.064","description":"Euro","rate_float":49114.064},"CNY":{"code":"CNY","symbol":"&yen;","rate":"386,120.315","description":"Chinese Yuan","rate_float":386120.3152}}}