{"time":{"updated":"Jul 6, 2023 00:28:00 UTC","updatedISO":"2023-07-06T00:28:00+00:00","updateduk":"Jul 6, 2023 at 01:28 BST"},"disclaimer":"This data was produced from the CoinDesk Bitcoin Price Index (USD). Non-USD currency data converted using hourly conversion rate from openexchangerates.org","chartName":"Bitcoin","bpi":{"USD":{"code":"USD","symbol":"&#36;","rate":"30,502.3742","description":"United States Dollar","rate_float":30502.3742},"GBP":{"code":"GBP","symbol":"&pound;","rate":"25,487.5399","description":"British Pound Sterling","rate_float":25487.5399},"EUR":{"code":"EUR","symbol":"&euro;","rate":"29,713.7658","description":"Euro","rate_float":29713.7658},"CNY":{"code":"CNY","symbol":"&yen;","rate":"40,202.5000","description":"Chinese Yuan","rate_float":40202.5}}}