{"time":{"updated":"Mar 24, 2024 17:05:45 UTC","updatedISO":"2024-03-24T17:05:45+00:00","updateduk":"Mar 24, 2024 at 17:05 GMT"},"disclaimer":"This data was produced from the CoinDesk Bitcoin Price Index (USD). Non-USD currency data converted using hourly conversion rate from openexchangerates.org","chartName":"Bitcoin","bpi":{"USD":{"code":"USD","symbol":"&#36;","rate":"65,167.975","description":"United States Dollar","rate_float":65167.9753},"GBP":{"code":"GBP","symbol":"&pound;","rate":"51,716.523","description":"British Pound Sterling","rate_float":51716.5232},"EUR":{"code":"EUR","symbol":"&euro;","rate":"59,988.49","description":"Euro","rate_float":59988.4898},"CNY":{"code":"CNY","symbol":"&yen;","rate":"471,073.226","description":"Chinese Yuan","rate_float":471073.2263}}}