{"time":{"updated":"Oct 26, 2024 05:06:24 UTC","updatedISO":"2024-10-26T05:06:24+00:00","updateduk":"Oct 26, 2024 at 06:06 BST"},"disclaimer":"This data was produced from the CoinDesk Bitcoin Price Index (USD). Non-USD currency data converted using hourly conversion rate from openexchangerates.org","chartName":"Bitcoin","bpi":{"USD":{"code":"USD","symbol":"&#36;","rate":"66,961.34","description":"United States Dollar","rate_float":66961.3401},"GBP":{"code":"GBP","symbol":"&pound;","rate":"51,663.687","description":"British Pound Sterling","rate_float":51663.6872},"EUR":{"code":"EUR","symbol":"&euro;","rate":"61,997.764","description":"Euro","rate_float":61997.7638},"CNY":{"code":"CNY","symbol":"&yen;","rate":"476,838.399","description":"Chinese Yuan","rate_float":476838.399}}}