{"time":{"updated":"Mar 1, 2024 21:06:04 UTC","updatedISO":"2024-03-01T21:06:04+00:00","updateduk":"Mar 1, 2024 at 21:06 GMT"},"disclaimer":"This data was produced from the CoinDesk Bitcoin Price Index (USD). Non-USD currency data converted using hourly conversion rate from openexchangerates.org","chartName":"Bitcoin","bpi":{"USD":{"code":"USD","symbol":"&#36;","rate":"62,633.978","description":"United States Dollar","rate_float":62633.9775},"GBP":{"code":"GBP","symbol":"&pound;","rate":"49,463.743","description":"British Pound Sterling","rate_float":49463.7431},"EUR":{"code":"EUR","symbol":"&euro;","rate":"57,771.952","description":"Euro","rate_float":57771.9523},"CNY":{"code":"CNY","symbol":"&yen;","rate":"450,751.682","description":"Chinese Yuan","rate_float":450751.6823}}}