{"time":{"updated":"Apr 16, 2024 12:59:41 UTC","updatedISO":"2024-04-16T12:59:41+00:00","updateduk":"Apr 16, 2024 at 13:59 BST"},"disclaimer":"This data was produced from the CoinDesk Bitcoin Price Index (USD). Non-USD currency data converted using hourly conversion rate from openexchangerates.org","chartName":"Bitcoin","bpi":{"USD":{"code":"USD","symbol":"&#36;","rate":"63,146.216","description":"United States Dollar","rate_float":63146.2161},"GBP":{"code":"GBP","symbol":"&pound;","rate":"50,687.847","description":"British Pound Sterling","rate_float":50687.8466},"EUR":{"code":"EUR","symbol":"&euro;","rate":"59,335.153","description":"Euro","rate_float":59335.1526},"CNY":{"code":"CNY","symbol":"&yen;","rate":"457,083.886","description":"Chinese Yuan","rate_float":457083.8855}}}