{"time":{"updated":"Dec 8, 2024 21:06:06 UTC","updatedISO":"2024-12-08T21:06:06+00:00","updateduk":"Dec 8, 2024 at 21:06 GMT"},"disclaimer":"This data was produced from the CoinDesk Bitcoin Price Index (USD). Non-USD currency data converted using hourly conversion rate from openexchangerates.org","chartName":"Bitcoin","bpi":{"USD":{"code":"USD","symbol":"&#36;","rate":"99,686.31","description":"United States Dollar","rate_float":99686.3095},"GBP":{"code":"GBP","symbol":"&pound;","rate":"78,277.478","description":"British Pound Sterling","rate_float":78277.4783},"EUR":{"code":"EUR","symbol":"&euro;","rate":"94,402.138","description":"Euro","rate_float":94402.1376},"CNY":{"code":"CNY","symbol":"&yen;","rate":"724,749.376","description":"Chinese Yuan","rate_float":724749.3756}}}