{"time":{"updated":"Mar 16, 2024 07:05:35 UTC","updatedISO":"2024-03-16T07:05:35+00:00","updateduk":"Mar 16, 2024 at 07:05 GMT"},"disclaimer":"This data was produced from the CoinDesk Bitcoin Price Index (USD). Non-USD currency data converted using hourly conversion rate from openexchangerates.org","chartName":"Bitcoin","bpi":{"USD":{"code":"USD","symbol":"&#36;","rate":"69,256.183","description":"United States Dollar","rate_float":69256.1833},"GBP":{"code":"GBP","symbol":"&pound;","rate":"54,399.624","description":"British Pound Sterling","rate_float":54399.6239},"EUR":{"code":"EUR","symbol":"&euro;","rate":"63,594.49","description":"Euro","rate_float":63594.4903},"CNY":{"code":"CNY","symbol":"&yen;","rate":"498,367.495","description":"Chinese Yuan","rate_float":498367.4953}}}