{"time":{"updated":"May 21, 2024 19:06:20 UTC","updatedISO":"2024-05-21T19:06:20+00:00","updateduk":"May 21, 2024 at 20:06 BST"},"disclaimer":"This data was produced from the CoinDesk Bitcoin Price Index (USD). Non-USD currency data converted using hourly conversion rate from openexchangerates.org","chartName":"Bitcoin","bpi":{"USD":{"code":"USD","symbol":"&#36;","rate":"69,701.008","description":"United States Dollar","rate_float":69701.0076},"GBP":{"code":"GBP","symbol":"&pound;","rate":"54,838.941","description":"British Pound Sterling","rate_float":54838.9406},"EUR":{"code":"EUR","symbol":"&euro;","rate":"64,220.905","description":"Euro","rate_float":64220.9053},"CNY":{"code":"CNY","symbol":"&yen;","rate":"494,319.546","description":"Chinese Yuan","rate_float":494319.5459}}}