{"time":{"updated":"Sep 11, 2024 16:07:21 UTC","updatedISO":"2024-09-11T16:07:21+00:00","updateduk":"Sep 11, 2024 at 17:07 BST"},"disclaimer":"This data was produced from the CoinDesk Bitcoin Price Index (USD). Non-USD currency data converted using hourly conversion rate from openexchangerates.org","chartName":"Bitcoin","bpi":{"USD":{"code":"USD","symbol":"&#36;","rate":"57,040.368","description":"United States Dollar","rate_float":57040.3675},"GBP":{"code":"GBP","symbol":"&pound;","rate":"43,828.107","description":"British Pound Sterling","rate_float":43828.1072},"EUR":{"code":"EUR","symbol":"&euro;","rate":"51,807.313","description":"Euro","rate_float":51807.3131},"CNY":{"code":"CNY","symbol":"&yen;","rate":"406,104.6","description":"Chinese Yuan","rate_float":406104.6004}}}