{"time":{"updated":"Dec 20, 2023 07:05:00 UTC","updatedISO":"2023-12-20T07:05:00+00:00","updateduk":"Dec 20, 2023 at 07:05 GMT"},"disclaimer":"This data was produced from the CoinDesk Bitcoin Price Index (USD). Non-USD currency data converted using hourly conversion rate from openexchangerates.org","chartName":"Bitcoin","bpi":{"USD":{"code":"USD","symbol":"&#36;","rate":"42,846.7335","description":"United States Dollar","rate_float":42846.7335},"GBP":{"code":"GBP","symbol":"&pound;","rate":"35,802.3878","description":"British Pound Sterling","rate_float":35802.3878},"EUR":{"code":"EUR","symbol":"&euro;","rate":"41,738.9741","description":"Euro","rate_float":41738.9741},"CNY":{"code":"CNY","symbol":"&yen;","rate":"40,202.5000","description":"Chinese Yuan","rate_float":40202.5}}}