{"time":{"updated":"Apr 17, 2024 08:07:03 UTC","updatedISO":"2024-04-17T08:07:03+00:00","updateduk":"Apr 17, 2024 at 09:07 BST"},"disclaimer":"This data was produced from the CoinDesk Bitcoin Price Index (USD). Non-USD currency data converted using hourly conversion rate from openexchangerates.org","chartName":"Bitcoin","bpi":{"USD":{"code":"USD","symbol":"&#36;","rate":"63,493.811","description":"United States Dollar","rate_float":63493.8113},"GBP":{"code":"GBP","symbol":"&pound;","rate":"50,902.798","description":"British Pound Sterling","rate_float":50902.7981},"EUR":{"code":"EUR","symbol":"&euro;","rate":"59,705.072","description":"Euro","rate_float":59705.0721},"CNY":{"code":"CNY","symbol":"&yen;","rate":"459,549.158","description":"Chinese Yuan","rate_float":459549.1582}}}