{"time":{"updated":"Jun 2, 2024 05:06:21 UTC","updatedISO":"2024-06-02T05:06:21+00:00","updateduk":"Jun 2, 2024 at 06:06 BST"},"disclaimer":"This data was produced from the CoinDesk Bitcoin Price Index (USD). Non-USD currency data converted using hourly conversion rate from openexchangerates.org","chartName":"Bitcoin","bpi":{"USD":{"code":"USD","symbol":"&#36;","rate":"67,871.449","description":"United States Dollar","rate_float":67871.4494},"GBP":{"code":"GBP","symbol":"&pound;","rate":"53,286.825","description":"British Pound Sterling","rate_float":53286.8251},"EUR":{"code":"EUR","symbol":"&euro;","rate":"62,516.867","description":"Euro","rate_float":62516.8671},"CNY":{"code":"CNY","symbol":"&yen;","rate":"482,287.732","description":"Chinese Yuan","rate_float":482287.7323}}}