{"time":{"updated":"Feb 3, 2024 08:05:59 UTC","updatedISO":"2024-02-03T08:05:59+00:00","updateduk":"Feb 3, 2024 at 08:05 GMT"},"disclaimer":"This data was produced from the CoinDesk Bitcoin Price Index (USD). Non-USD currency data converted using hourly conversion rate from openexchangerates.org","chartName":"Bitcoin","bpi":{"USD":{"code":"USD","symbol":"&#36;","rate":"43,079.476","description":"United States Dollar","rate_float":43079.4755},"GBP":{"code":"GBP","symbol":"&pound;","rate":"34,100.765","description":"British Pound Sterling","rate_float":34100.765},"EUR":{"code":"EUR","symbol":"&euro;","rate":"39,893.748","description":"Euro","rate_float":39893.7482},"CNY":{"code":"CNY","symbol":"&yen;","rate":"309,823.28","description":"Chinese Yuan","rate_float":309823.2795}}}