{"time":{"updated":"Dec 19, 2024 05:07:26 UTC","updatedISO":"2024-12-19T05:07:26+00:00","updateduk":"Dec 19, 2024 at 05:07 GMT"},"disclaimer":"This data was produced from the CoinDesk Bitcoin Price Index (USD). Non-USD currency data converted using hourly conversion rate from openexchangerates.org","chartName":"Bitcoin","bpi":{"USD":{"code":"USD","symbol":"&#36;","rate":"102,176.01","description":"United States Dollar","rate_float":102176.01},"GBP":{"code":"GBP","symbol":"&pound;","rate":"79,949.969","description":"British Pound Sterling","rate_float":79949.9691},"EUR":{"code":"EUR","symbol":"&euro;","rate":"97,021.23","description":"Euro","rate_float":97021.2303},"CNY":{"code":"CNY","symbol":"&yen;","rate":"740,745.42","description":"Chinese Yuan","rate_float":740745.4199}}}