{"time":{"updated":"Mar 24, 2024 03:06:18 UTC","updatedISO":"2024-03-24T03:06:18+00:00","updateduk":"Mar 24, 2024 at 03:06 GMT"},"disclaimer":"This data was produced from the CoinDesk Bitcoin Price Index (USD). Non-USD currency data converted using hourly conversion rate from openexchangerates.org","chartName":"Bitcoin","bpi":{"USD":{"code":"USD","symbol":"&#36;","rate":"64,366.145","description":"United States Dollar","rate_float":64366.1454},"GBP":{"code":"GBP","symbol":"&pound;","rate":"51,080.201","description":"British Pound Sterling","rate_float":51080.2006},"EUR":{"code":"EUR","symbol":"&euro;","rate":"59,278.002","description":"Euro","rate_float":59278.0016},"CNY":{"code":"CNY","symbol":"&yen;","rate":"465,277.119","description":"Chinese Yuan","rate_float":465277.119}}}