{"time":{"updated":"Jan 29, 2025 21:20:08 UTC","updatedISO":"2025-01-29T21:20:08+00:00","updateduk":"Jan 29, 2025 at 21:20 GMT"},"disclaimer":"This data was produced from the CoinDesk Bitcoin Price Index (USD). Non-USD currency data converted using hourly conversion rate from openexchangerates.org","chartName":"Bitcoin","bpi":{"USD":{"code":"USD","symbol":"&#36;","rate":"104,686.512","description":"United States Dollar","rate_float":104686.5117},"GBP":{"code":"GBP","symbol":"&pound;","rate":"84,072.377","description":"British Pound Sterling","rate_float":84072.3767},"EUR":{"code":"EUR","symbol":"&euro;","rate":"100,088.366","description":"Euro","rate_float":100088.3661},"CNY":{"code":"CNY","symbol":"&yen;","rate":"760,725.475","description":"Chinese Yuan","rate_float":760725.4749}}}