{"time":{"updated":"Nov 4, 2024 02:31:24 UTC","updatedISO":"2024-11-04T02:31:24+00:00","updateduk":"Nov 4, 2024 at 02:31 GMT"},"disclaimer":"This data was produced from the CoinDesk Bitcoin Price Index (USD). Non-USD currency data converted using hourly conversion rate from openexchangerates.org","chartName":"Bitcoin","bpi":{"USD":{"code":"USD","symbol":"&#36;","rate":"69,141.491","description":"United States Dollar","rate_float":69141.4914},"GBP":{"code":"GBP","symbol":"&pound;","rate":"53,287.278","description":"British Pound Sterling","rate_float":53287.2783},"EUR":{"code":"EUR","symbol":"&euro;","rate":"63,501.067","description":"Euro","rate_float":63501.0668},"CNY":{"code":"CNY","symbol":"&yen;","rate":"491,893.312","description":"Chinese Yuan","rate_float":491893.3121}}}