{"time":{"updated":"Jan 15, 2024 22:05:56 UTC","updatedISO":"2024-01-15T22:05:56+00:00","updateduk":"Jan 15, 2024 at 22:05 GMT"},"disclaimer":"This data was produced from the CoinDesk Bitcoin Price Index (USD). Non-USD currency data converted using hourly conversion rate from openexchangerates.org","chartName":"Bitcoin","bpi":{"USD":{"code":"USD","symbol":"&#36;","rate":"42,750.919","description":"United States Dollar","rate_float":42750.9193},"GBP":{"code":"GBP","symbol":"&pound;","rate":"33,591.663","description":"British Pound Sterling","rate_float":33591.6631},"EUR":{"code":"EUR","symbol":"&euro;","rate":"39,034.796","description":"Euro","rate_float":39034.7956},"CNY":{"code":"CNY","symbol":"&yen;","rate":"303,779.482","description":"Chinese Yuan","rate_float":303779.482}}}