{"time":{"updated":"Feb 7, 2023 04:05:00 UTC","updatedISO":"2023-02-07T04:05:00+00:00","updateduk":"Feb 7, 2023 at 04:05 GMT"},"disclaimer":"This data was produced from the CoinDesk Bitcoin Price Index (USD). Non-USD currency data converted using hourly conversion rate from openexchangerates.org","chartName":"Bitcoin","bpi":{"USD":{"code":"USD","symbol":"&#36;","rate":"22,876.1966","description":"United States Dollar","rate_float":22876.1966},"GBP":{"code":"GBP","symbol":"&pound;","rate":"19,115.1668","description":"British Pound Sterling","rate_float":19115.1668},"EUR":{"code":"EUR","symbol":"&euro;","rate":"22,284.7554","description":"Euro","rate_float":22284.7554},"CNY":{"code":"CNY","symbol":"&yen;","rate":"40,202.5000","description":"Chinese Yuan","rate_float":40202.5}}}