{"time":{"updated":"Jun 4, 2024 19:05:48 UTC","updatedISO":"2024-06-04T19:05:48+00:00","updateduk":"Jun 4, 2024 at 20:05 BST"},"disclaimer":"This data was produced from the CoinDesk Bitcoin Price Index (USD). Non-USD currency data converted using hourly conversion rate from openexchangerates.org","chartName":"Bitcoin","bpi":{"USD":{"code":"USD","symbol":"&#36;","rate":"70,625.276","description":"United States Dollar","rate_float":70625.276},"GBP":{"code":"GBP","symbol":"&pound;","rate":"55,256.086","description":"British Pound Sterling","rate_float":55256.0859},"EUR":{"code":"EUR","symbol":"&euro;","rate":"64,899.544","description":"Euro","rate_float":64899.5436},"CNY":{"code":"CNY","symbol":"&yen;","rate":"511,319.936","description":"Chinese Yuan","rate_float":511319.9357}}}