{"time":{"updated":"Jan 22, 2025 13:10:04 UTC","updatedISO":"2025-01-22T13:10:04+00:00","updateduk":"Jan 22, 2025 at 13:10 GMT"},"disclaimer":"This data was produced from the CoinDesk Bitcoin Price Index (USD). Non-USD currency data converted using hourly conversion rate from openexchangerates.org","chartName":"Bitcoin","bpi":{"USD":{"code":"USD","symbol":"&#36;","rate":"104,691.793","description":"United States Dollar","rate_float":104691.7933},"GBP":{"code":"GBP","symbol":"&pound;","rate":"83,499.557","description":"British Pound Sterling","rate_float":83499.557},"EUR":{"code":"EUR","symbol":"&euro;","rate":"100,685.657","description":"Euro","rate_float":100685.6571},"CNY":{"code":"CNY","symbol":"&yen;","rate":"767,170.992","description":"Chinese Yuan","rate_float":767170.9922}}}