{"time":{"updated":"Mar 19, 2023 12:07:00 UTC","updatedISO":"2023-03-19T12:07:00+00:00","updateduk":"Mar 19, 2023 at 12:07 GMT"},"disclaimer":"This data was produced from the CoinDesk Bitcoin Price Index (USD). Non-USD currency data converted using hourly conversion rate from openexchangerates.org","chartName":"Bitcoin","bpi":{"USD":{"code":"USD","symbol":"&#36;","rate":"27,303.0315","description":"United States Dollar","rate_float":27303.0315},"GBP":{"code":"GBP","symbol":"&pound;","rate":"22,814.1947","description":"British Pound Sterling","rate_float":22814.1947},"EUR":{"code":"EUR","symbol":"&euro;","rate":"26,597.1389","description":"Euro","rate_float":26597.1389},"CNY":{"code":"CNY","symbol":"&yen;","rate":"40,202.5000","description":"Chinese Yuan","rate_float":40202.5}}}