{"time":{"updated":"Dec 22, 2022 00:22:00 UTC","updatedISO":"2022-12-22T00:22:00+00:00","updateduk":"Dec 22, 2022 at 00:22 GMT"},"disclaimer":"This data was produced from the CoinDesk Bitcoin Price Index (USD). Non-USD currency data converted using hourly conversion rate from openexchangerates.org","chartName":"Bitcoin","bpi":{"USD":{"code":"USD","symbol":"&#36;","rate":"16,812.3041","description":"United States Dollar","rate_float":16812.3041},"GBP":{"code":"GBP","symbol":"&pound;","rate":"14,048.2268","description":"British Pound Sterling","rate_float":14048.2268},"EUR":{"code":"EUR","symbol":"&euro;","rate":"16,377.6387","description":"Euro","rate_float":16377.6387},"CNY":{"code":"CNY","symbol":"&yen;","rate":"40,202.5000","description":"Chinese Yuan","rate_float":40202.5}}}