{"time":{"updated":"Jun 20, 2024 11:05:47 UTC","updatedISO":"2024-06-20T11:05:47+00:00","updateduk":"Jun 20, 2024 at 12:05 BST"},"disclaimer":"This data was produced from the CoinDesk Bitcoin Price Index (USD). Non-USD currency data converted using hourly conversion rate from openexchangerates.org","chartName":"Bitcoin","bpi":{"USD":{"code":"USD","symbol":"&#36;","rate":"66,207.594","description":"United States Dollar","rate_float":66207.5936},"GBP":{"code":"GBP","symbol":"&pound;","rate":"52,106.105","description":"British Pound Sterling","rate_float":52106.1045},"EUR":{"code":"EUR","symbol":"&euro;","rate":"61,730.967","description":"Euro","rate_float":61730.9672},"CNY":{"code":"CNY","symbol":"&yen;","rate":"480,693.613","description":"Chinese Yuan","rate_float":480693.6127}}}