{"time":{"updated":"Mar 26, 2024 17:05:43 UTC","updatedISO":"2024-03-26T17:05:43+00:00","updateduk":"Mar 26, 2024 at 17:05 GMT"},"disclaimer":"This data was produced from the CoinDesk Bitcoin Price Index (USD). Non-USD currency data converted using hourly conversion rate from openexchangerates.org","chartName":"Bitcoin","bpi":{"USD":{"code":"USD","symbol":"&#36;","rate":"69,848.469","description":"United States Dollar","rate_float":69848.4689},"GBP":{"code":"GBP","symbol":"&pound;","rate":"55,310.069","description":"British Pound Sterling","rate_float":55310.0689},"EUR":{"code":"EUR","symbol":"&euro;","rate":"64,503.874","description":"Euro","rate_float":64503.8736},"CNY":{"code":"CNY","symbol":"&yen;","rate":"504,194.188","description":"Chinese Yuan","rate_float":504194.1877}}}