{"time":{"updated":"Sep 20, 2024 07:07:07 UTC","updatedISO":"2024-09-20T07:07:07+00:00","updateduk":"Sep 20, 2024 at 08:07 BST"},"disclaimer":"This data was produced from the CoinDesk Bitcoin Price Index (USD). Non-USD currency data converted using hourly conversion rate from openexchangerates.org","chartName":"Bitcoin","bpi":{"USD":{"code":"USD","symbol":"&#36;","rate":"63,652.602","description":"United States Dollar","rate_float":63652.6015},"GBP":{"code":"GBP","symbol":"&pound;","rate":"47,876.941","description":"British Pound Sterling","rate_float":47876.9407},"EUR":{"code":"EUR","symbol":"&euro;","rate":"57,014.845","description":"Euro","rate_float":57014.8445},"CNY":{"code":"CNY","symbol":"&yen;","rate":"448,413.482","description":"Chinese Yuan","rate_float":448413.4816}}}