{"time":{"updated":"Dec 28, 2024 13:08:24 UTC","updatedISO":"2024-12-28T13:08:24+00:00","updateduk":"Dec 28, 2024 at 13:08 GMT"},"disclaimer":"This data was produced from the CoinDesk Bitcoin Price Index (USD). Non-USD currency data converted using hourly conversion rate from openexchangerates.org","chartName":"Bitcoin","bpi":{"USD":{"code":"USD","symbol":"&#36;","rate":"94,577.549","description":"United States Dollar","rate_float":94577.5485},"GBP":{"code":"GBP","symbol":"&pound;","rate":"75,423.703","description":"British Pound Sterling","rate_float":75423.7034},"EUR":{"code":"EUR","symbol":"&euro;","rate":"90,734.957","description":"Euro","rate_float":90734.9573},"CNY":{"code":"CNY","symbol":"&yen;","rate":"690,283.695","description":"Chinese Yuan","rate_float":690283.6954}}}