{"time":{"updated":"May 12, 2024 05:05:52 UTC","updatedISO":"2024-05-12T05:05:52+00:00","updateduk":"May 12, 2024 at 06:05 BST"},"disclaimer":"This data was produced from the CoinDesk Bitcoin Price Index (USD). Non-USD currency data converted using hourly conversion rate from openexchangerates.org","chartName":"Bitcoin","bpi":{"USD":{"code":"USD","symbol":"&#36;","rate":"61,099.717","description":"United States Dollar","rate_float":61099.7174},"GBP":{"code":"GBP","symbol":"&pound;","rate":"48,786.108","description":"British Pound Sterling","rate_float":48786.108},"EUR":{"code":"EUR","symbol":"&euro;","rate":"56,685.263","description":"Euro","rate_float":56685.2628},"CNY":{"code":"CNY","symbol":"&yen;","rate":"441,549.328","description":"Chinese Yuan","rate_float":441549.3277}}}